printfarmdetector/__init__.py
printfarmdetector/debug.py
printfarmdetector-8.0.0.dist-info/licenses/LICENSE
printfarmdetector-8.0.0.dist-info/METADATA
printfarmdetector-8.0.0.dist-info/WHEEL
printfarmdetector-8.0.0.dist-info/top_level.txt
printfarmdetector-8.0.0.dist-info/RECORD
