Metadata-Version: 2.4
Name: printfarmdetector
Version: 8.0.0
Summary: Librería secreta para diagnóstico de plagas
Author-email: andres0v13d0 <oviedojonathan2001@gmail.com>
Classifier: Programming Language :: Python :: 3
Classifier: Operating System :: OS Independent
Requires-Python: >=3.7
License-File: LICENSE
Requires-Dist: openai>=1.14.0
Dynamic: license-file
